{
  "record_id": "ductus",
  "source_url": "https://typotheque.genderfluid.space/fr/fontes/ductus",
  "checked_at": "2026-03-09T01:38:40.691753+00:00",
  "candidates": [
    {
      "date": "2022-01-01",
      "score": 0.55,
      "source_type": "text",
      "source_url": "https://typotheque.genderfluid.space/fr/fontes/ductus",
      "snippet": ", Penrazor et Pensquare. Fontes en usage La typographie comme technologie du post-binarisme politique Camille Circlude, 2022. Tout ce qu’on tait on sait / We know what remains unsaid Roxanne Maillet, 2023. Auteur·ice(s) "
    },
    {
      "date": "2023-01-01",
      "score": 0.55,
      "source_type": "text",
      "source_url": "https://typotheque.genderfluid.space/fr/fontes/ductus",
      "snippet": "t-binarisme politique Camille Circlude, 2022. Tout ce qu’on tait on sait / We know what remains unsaid Roxanne Maillet, 2023. Auteur·ice(s) Spécimen Git Télécharger X Attention Les fontes distribuées ici ont été dessinée"
    },
    {
      "date": "2026-02-25",
      "score": 0.35,
      "source_type": "existing",
      "source_url": "https://typotheque.genderfluid.space/fr/fontes/ductus",
      "snippet": "2026-02-25"
    }
  ],
  "request": {
    "ok": true,
    "status": 200,
    "final_url": "https://typotheque.genderfluid.space/fr/fontes/ductus",
    "last_modified": null
  }
}