{
  "record_id": "gothiks-compressed",
  "source_url": "http://blackletra.com/typefaces/gothiks-compressed",
  "checked_at": "2026-03-09T01:46:24.189870+00:00",
  "candidates": [
    {
      "date": "2023-07-28",
      "score": 0.75,
      "source_type": "meta:date",
      "source_url": "https://blackletra.com/typefaces/gothiks-compressed",
      "snippet": "2023-07-28"
    },
    {
      "date": "2016-01-01",
      "score": 0.55,
      "source_type": "text",
      "source_url": "https://blackletra.com/typefaces/gothiks-compressed",
      "snippet": " Wik-Mungkan Wiradjuri Wolof Xavante Xhosa Yapese Yindjibarndi Zapotec Zarma Zazaki Zulu Zuni Design Daniel Sabino Year 2016 Related Gothiks Gothiks Condensed Gothiks Round Compressed Gothiks Round Condensed Gothiks Roun"
    },
    {
      "date": "2026-02-25",
      "score": 0.35,
      "source_type": "existing",
      "source_url": "http://blackletra.com/typefaces/gothiks-compressed",
      "snippet": "2026-02-25"
    }
  ],
  "request": {
    "ok": true,
    "status": 200,
    "final_url": "https://blackletra.com/typefaces/gothiks-compressed",
    "last_modified": null
  }
}