{
  "record_id": "ivar-display-condensed",
  "source_url": "https://lettersfromsweden.se/font/ivar-display-condensed",
  "checked_at": "2026-03-09T01:39:40.912439+00:00",
  "candidates": [
    {
      "date": "2019-01-01",
      "score": 0.55,
      "source_type": "text",
      "source_url": "https://lettersfromsweden.se/font/ivar-display-condensed/",
      "snippet": "sed Web quantity Add to cart More page views or a custom license? Contact us . Malmsten Hellberg Tidskriften Arkitektur 2019 Letters from Sweden Fonts , Custom , Trials , & More Cart → € 0 A Adelia BAZAAR Blåkulla Capita"
    },
    {
      "date": "2026-01-01",
      "score": 0.45,
      "source_type": "http:last-modified",
      "source_url": "https://lettersfromsweden.se/font/ivar-display-condensed/",
      "snippet": "Mon, 09 Mar 2026 01:39:42 GMT"
    },
    {
      "date": "2026-02-25",
      "score": 0.35,
      "source_type": "existing",
      "source_url": "https://lettersfromsweden.se/font/ivar-display-condensed",
      "snippet": "2026-02-25"
    }
  ],
  "request": {
    "ok": true,
    "status": 200,
    "final_url": "https://lettersfromsweden.se/font/ivar-display-condensed/",
    "last_modified": "Mon, 09 Mar 2026 01:39:42 GMT"
  }
}