{
  "record_id": "sets-grotesk",
  "source_url": "https://www.dograytype.com/fonts/sets-grotesk",
  "checked_at": "2026-03-09T01:59:27.266820+00:00",
  "candidates": [
    {
      "date": "2025-01-01",
      "score": 0.55,
      "source_type": "text",
      "source_url": "https://www.dograytype.com/fonts/sets-grotesk",
      "snippet": "k Sets Grotesk STYLES 4 optical sizes with 9 weights each, 36 styles total FORMATS Desktop, App – TTF, Web – WOFF2 YEAR 2025 LATEST VERSION v1.000 SUPPORTED SCRIPTS Latin CONCEPT José Solé DESIGN José Solé & Sahar Afshar"
    },
    {
      "date": "2026-01-01",
      "score": 0.45,
      "source_type": "http:last-modified",
      "source_url": "https://www.dograytype.com/fonts/sets-grotesk",
      "snippet": "Fri, 06 Mar 2026 17:33:39 GMT"
    },
    {
      "date": "2026-02-25",
      "score": 0.35,
      "source_type": "existing",
      "source_url": "https://www.dograytype.com/fonts/sets-grotesk",
      "snippet": "2026-02-25"
    }
  ],
  "request": {
    "ok": true,
    "status": 200,
    "final_url": "https://www.dograytype.com/fonts/sets-grotesk",
    "last_modified": "Fri, 06 Mar 2026 17:33:39 GMT"
  }
}