{
  "record_id": "staff-grotesk",
  "source_url": "https://www.r-typography.com/fonts/staff-grotesk",
  "checked_at": "2026-03-09T01:52:43.811479+00:00",
  "candidates": [
    {
      "date": "2026-01-01",
      "score": 0.45,
      "source_type": "http:last-modified",
      "source_url": "https://www.r-typography.com/fonts/staff-grotesk",
      "snippet": "Fri, 23 Jan 2026 13:53:00 GMT"
    },
    {
      "date": "2026-02-25",
      "score": 0.35,
      "source_type": "existing",
      "source_url": "https://www.r-typography.com/fonts/staff-grotesk",
      "snippet": "2026-02-25"
    }
  ],
  "request": {
    "ok": true,
    "status": 200,
    "final_url": "https://www.r-typography.com/fonts/staff-grotesk",
    "last_modified": "Fri, 23 Jan 2026 13:53:00 GMT"
  }
}